mxboxutils/__init__.py
mxboxutils/file.py
mxboxutils/toml.py
mxboxutils-0.1.6.dist-info/licenses/LICENSE
mxboxutils-0.1.6.dist-info/METADATA
mxboxutils-0.1.6.dist-info/WHEEL
mxboxutils-0.1.6.dist-info/top_level.txt
mxboxutils-0.1.6.dist-info/RECORD
